helloworld.py
credmarkutils-0.0.1.dist-info/LICENSE.txt
credmarkutils-0.0.1.dist-info/METADATA
credmarkutils-0.0.1.dist-info/WHEEL
credmarkutils-0.0.1.dist-info/top_level.txt
credmarkutils-0.0.1.dist-info/RECORD
