Metadata-Version: 2.1
Name: credmarkutils
Version: 0.0.1
Summary: Credmark Utils
Home-page: https://github.com/credmark/credmarkutils
Author: Nishchal Gaba
Author-email: nishchal@credmark.com
License: UNKNOWN
Platform: UNKNOWN
Provides-Extra: dev
Requires-Dist: pytest (>=3.7) ; extra == 'dev'
